wscli/__init__.py
wscli/api_utils/__init__.py
wscli/api_utils/api_endpoint.py
wscli/api_utils/api_url.py
wscli/api_utils/async_jobs.py
wscli/api_utils/call_config.py
wscli/api_utils/utils.py
wscli/auth/__init__.py
wscli/auth/cognito.py
wscli/auth/keycloak.py
wscli/auth/login.py
wscli/auth/login_tokens.py
wscli/auth/profiles.py
wscli/auth/signin_details.py
wscli/auth/token.py
wscli/clis/__init__.py
wscli/clis/auth.py
wscli/clis/config.py
wscli/clis/ml.py
wscli/config.py
wscli/scripts/__init__.py
wscli/scripts/wscli.py
wscli/utils.py
wscli-0.4.0.dist-info/METADATA
wscli-0.4.0.dist-info/WHEEL
wscli-0.4.0.dist-info/entry_points.txt
wscli-0.4.0.dist-info/RECORD
