Metadata-Version: 2.1
Name: wscli
Version: 0.4.0
Summary: 
Author: Lorenzo Trojan
Author-email: ltrojan@wildersensing.com
Requires-Python: >=3.10,<4.0
Classifier: Programming Language :: Python :: 3
Classifier: Programming Language :: Python :: 3.10
Classifier: Programming Language :: Python :: 3.11
Classifier: Programming Language :: Python :: 3.12
Requires-Dist: boto3 (>=1.34.136,<2.0.0)
Requires-Dist: click (>=8.1.7,<9.0.0)
Requires-Dist: pydantic (==2.7.4)
Requires-Dist: pyjwt (>=2.8.0,<3.0.0)
Requires-Dist: pyyaml (>=6.0.2,<7.0.0)
Requires-Dist: requests (>=2.32.2,<3.0.0)
